mkidcore-1.9.0.dist-info/METADATA
mkidcore-1.9.0.dist-info/WHEEL
mkidcore-1.9.0.dist-info/licenses/LICENSE
mkidcore/__init__.py
mkidcore/binfile/__init__.py
mkidcore/binfile/binprocessor.c
mkidcore/binfile/binprocessor.h
mkidcore/binfile/mkidbin.c
mkidcore/binfile/mkidbin.cpython-312-x86_64-linux-gnu.so
mkidcore/binfile/mkidbin.pyx
mkidcore/conex_pixel_mapping
mkidcore/config.py
mkidcore/corelog.py
mkidcore/corelog.yaml
mkidcore/darkness.bmap
mkidcore/fits.py
mkidcore/instruments.py
mkidcore/legacy.py
mkidcore/mec.bmap
mkidcore/mec_feedline.txt
mkidcore/mec_keys.csv
mkidcore/metadata.py
mkidcore/notify.py
mkidcore/objects.py
mkidcore/pixelflags.py
mkidcore/readdict.py
mkidcore/safesocket.py
mkidcore/sweepdata.py
mkidcore/threads.py
mkidcore/utils.py
mkidcore/xkid.bmap
mkidcore/xkid_keys.csv
mkidcore-1.9.0.dist-info/RECORD
